{
    "codigoestacao": "66071390",
    "data": "2025-02-10",
    "dados": [
        {
            "Chuva_Adotada": "0.00",
            "Chuva_Adotada_Status": "0",
            "Cota_Adotada": "24878.00",
            "Cota_Adotada_Status": "0",
            "Data_Atualizacao": "2025-02-10 00:55:35.57",
            "Data_Hora_Medicao": "2025-02-10 00:00:00.0",
            "Vazao_Adotada": "69.80",
            "Vazao_Adotada_Status": "0"
        },
        {
            "Chuva_Adotada": "0.00",
            "Chuva_Adotada_Status": "0",
            "Cota_Adotada": "24875.00",
            "Cota_Adotada_Status": "0",
            "Data_Atualizacao": "2025-02-10 01:55:49.52",
            "Data_Hora_Medicao": "2025-02-10 01:00:00.0",
            "Vazao_Adotada": "70.96",
            "Vazao_Adotada_Status": "0"
        },
        {
            "Chuva_Adotada": "0.00",
            "Chuva_Adotada_Status": "0",
            "Cota_Adotada": "24875.00",
            "Cota_Adotada_Status": "0",
            "Data_Atualizacao": "2025-02-10 03:07:13.073",
            "Data_Hora_Medicao": "2025-02-10 02:00:00.0",
            "Vazao_Adotada": "72.88",
            "Vazao_Adotada_Status": "0"
        },
        {
            "Chuva_Adotada": null,
            "Chuva_Adotada_Status": "0",
            "Cota_Adotada": "24867.00",
            "Cota_Adotada_Status": "0",
            "Data_Atualizacao": "2025-02-10 03:07:13.113",
            "Data_Hora_Medicao": "2025-02-10 03:00:00.0",
            "Vazao_Adotada": "71.15",
            "Vazao_Adotada_Status": "0"
        },
        {
            "Chuva_Adotada": "0.00",
            "Chuva_Adotada_Status": "0",
            "Cota_Adotada": "24856.00",
            "Cota_Adotada_Status": "0",
            "Data_Atualizacao": "2025-02-10 04:55:21.933",
            "Data_Hora_Medicao": "2025-02-10 04:00:00.0",
            "Vazao_Adotada": "96.09",
            "Vazao_Adotada_Status": "0"
        },
        {
            "Chuva_Adotada": "0.00",
            "Chuva_Adotada_Status": "0",
            "Cota_Adotada": "24842.00",
            "Cota_Adotada_Status": "0",
            "Data_Atualizacao": "2025-02-10 05:56:16.603",
            "Data_Hora_Medicao": "2025-02-10 05:00:00.0",
            "Vazao_Adotada": "95.06",
            "Vazao_Adotada_Status": "0"
        },
        {
            "Chuva_Adotada": "0.00",
            "Chuva_Adotada_Status": "0",
            "Cota_Adotada": "24829.00",
            "Cota_Adotada_Status": "0",
            "Data_Atualizacao": "2025-02-10 06:55:16.543",
            "Data_Hora_Medicao": "2025-02-10 06:00:00.0",
            "Vazao_Adotada": "92.01",
            "Vazao_Adotada_Status": "0"
        },
        {
            "Chuva_Adotada": "0.00",
            "Chuva_Adotada_Status": "0",
            "Cota_Adotada": "24825.00",
            "Cota_Adotada_Status": "0",
            "Data_Atualizacao": "2025-02-10 07:55:13.83",
            "Data_Hora_Medicao": "2025-02-10 07:00:00.0",
            "Vazao_Adotada": "61.91",
            "Vazao_Adotada_Status": "0"
        },
        {
            "Chuva_Adotada": "0.00",
            "Chuva_Adotada_Status": "0",
            "Cota_Adotada": "24823.00",
            "Cota_Adotada_Status": "0",
            "Data_Atualizacao": "2025-02-10 08:59:23.34",
            "Data_Hora_Medicao": "2025-02-10 08:00:00.0",
            "Vazao_Adotada": "63.58",
            "Vazao_Adotada_Status": "0"
        },
        {
            "Chuva_Adotada": null,
            "Chuva_Adotada_Status": "0",
            "Cota_Adotada": "24812.00",
            "Cota_Adotada_Status": "0",
            "Data_Atualizacao": "2025-02-10 09:58:35.873",
            "Data_Hora_Medicao": "2025-02-10 09:00:00.0",
            "Vazao_Adotada": "63.34",
            "Vazao_Adotada_Status": "0"
        },
        {
            "Chuva_Adotada": "0.00",
            "Chuva_Adotada_Status": "0",
            "Cota_Adotada": null,
            "Cota_Adotada_Status": "0",
            "Data_Atualizacao": "2025-02-10 10:57:29.93",
            "Data_Hora_Medicao": "2025-02-10 10:00:00.0",
            "Vazao_Adotada": null,
            "Vazao_Adotada_Status": "0"
        },
        {
            "Chuva_Adotada": "0.00",
            "Chuva_Adotada_Status": "0",
            "Cota_Adotada": null,
            "Cota_Adotada_Status": "0",
            "Data_Atualizacao": "2025-02-10 11:57:44.74",
            "Data_Hora_Medicao": "2025-02-10 11:00:00.0",
            "Vazao_Adotada": null,
            "Vazao_Adotada_Status": "0"
        },
        {
            "Chuva_Adotada": "0.00",
            "Chuva_Adotada_Status": "0",
            "Cota_Adotada": null,
            "Cota_Adotada_Status": "0",
            "Data_Atualizacao": "2025-02-10 12:56:58.96",
            "Data_Hora_Medicao": "2025-02-10 12:00:00.0",
            "Vazao_Adotada": null,
            "Vazao_Adotada_Status": "0"
        },
        {
            "Chuva_Adotada": "0.20",
            "Chuva_Adotada_Status": "0",
            "Cota_Adotada": null,
            "Cota_Adotada_Status": "0",
            "Data_Atualizacao": "2025-02-10 13:58:17.413",
            "Data_Hora_Medicao": "2025-02-10 13:00:00.0",
            "Vazao_Adotada": null,
            "Vazao_Adotada_Status": "0"
        },
        {
            "Chuva_Adotada": "0.00",
            "Chuva_Adotada_Status": "0",
            "Cota_Adotada": null,
            "Cota_Adotada_Status": "0",
            "Data_Atualizacao": "2025-02-10 15:56:38.377",
            "Data_Hora_Medicao": "2025-02-10 14:00:00.0",
            "Vazao_Adotada": null,
            "Vazao_Adotada_Status": "0"
        },
        {
            "Chuva_Adotada": "3.60",
            "Chuva_Adotada_Status": "0",
            "Cota_Adotada": null,
            "Cota_Adotada_Status": "0",
            "Data_Atualizacao": "2025-02-10 15:56:38.42",
            "Data_Hora_Medicao": "2025-02-10 15:00:00.0",
            "Vazao_Adotada": null,
            "Vazao_Adotada_Status": "0"
        },
        {
            "Chuva_Adotada": "0.00",
            "Chuva_Adotada_Status": "0",
            "Cota_Adotada": null,
            "Cota_Adotada_Status": "0",
            "Data_Atualizacao": "2025-02-10 17:57:29.517",
            "Data_Hora_Medicao": "2025-02-10 17:00:00.0",
            "Vazao_Adotada": null,
            "Vazao_Adotada_Status": "0"
        },
        {
            "Chuva_Adotada": "0.00",
            "Chuva_Adotada_Status": "0",
            "Cota_Adotada": null,
            "Cota_Adotada_Status": "0",
            "Data_Atualizacao": "2025-02-10 18:58:28.383",
            "Data_Hora_Medicao": "2025-02-10 18:00:00.0",
            "Vazao_Adotada": null,
            "Vazao_Adotada_Status": "0"
        },
        {
            "Chuva_Adotada": "0.00",
            "Chuva_Adotada_Status": "0",
            "Cota_Adotada": null,
            "Cota_Adotada_Status": "0",
            "Data_Atualizacao": "2025-02-10 19:56:22.74",
            "Data_Hora_Medicao": "2025-02-10 19:00:00.0",
            "Vazao_Adotada": null,
            "Vazao_Adotada_Status": "0"
        },
        {
            "Chuva_Adotada": "0.00",
            "Chuva_Adotada_Status": "0",
            "Cota_Adotada": "24811.00",
            "Cota_Adotada_Status": "0",
            "Data_Atualizacao": "2025-02-10 21:05:42.887",
            "Data_Hora_Medicao": "2025-02-10 20:00:00.0",
            "Vazao_Adotada": "65.65",
            "Vazao_Adotada_Status": "0"
        },
        {
            "Chuva_Adotada": null,
            "Chuva_Adotada_Status": "0",
            "Cota_Adotada": "24812.00",
            "Cota_Adotada_Status": "0",
            "Data_Atualizacao": "2025-02-10 21:05:42.92",
            "Data_Hora_Medicao": "2025-02-10 21:00:00.0",
            "Vazao_Adotada": "90.44",
            "Vazao_Adotada_Status": "0"
        },
        {
            "Chuva_Adotada": "0.00",
            "Chuva_Adotada_Status": "0",
            "Cota_Adotada": "24808.00",
            "Cota_Adotada_Status": "0",
            "Data_Atualizacao": "2025-02-10 22:57:10.91",
            "Data_Hora_Medicao": "2025-02-10 22:00:00.0",
            "Vazao_Adotada": "68.64",
            "Vazao_Adotada_Status": "0"
        },
        {
            "Chuva_Adotada": "0.00",
            "Chuva_Adotada_Status": "0",
            "Cota_Adotada": "24805.00",
            "Cota_Adotada_Status": "0",
            "Data_Atualizacao": "2025-02-10 23:58:09.793",
            "Data_Hora_Medicao": "2025-02-10 23:00:00.0",
            "Vazao_Adotada": "66.63",
            "Vazao_Adotada_Status": "0"
        }
    ]
}