{
    "codigoestacao": "66005100",
    "data": "2025-03-16",
    "dados": [
        {
            "Chuva_Adotada": "0.00",
            "Chuva_Adotada_Status": "0",
            "Cota_Adotada": "67.00",
            "Cota_Adotada_Status": "0",
            "Data_Atualizacao": "2025-03-16 00:37:32.567",
            "Data_Hora_Medicao": "2025-03-16 00:00:00.0",
            "Vazao_Adotada": "4.90",
            "Vazao_Adotada_Status": "0"
        },
        {
            "Chuva_Adotada": "0.00",
            "Chuva_Adotada_Status": "0",
            "Cota_Adotada": "67.00",
            "Cota_Adotada_Status": "0",
            "Data_Atualizacao": "2025-03-16 01:27:49.16",
            "Data_Hora_Medicao": "2025-03-16 01:00:00.0",
            "Vazao_Adotada": "4.90",
            "Vazao_Adotada_Status": "0"
        },
        {
            "Chuva_Adotada": "0.00",
            "Chuva_Adotada_Status": "0",
            "Cota_Adotada": "67.00",
            "Cota_Adotada_Status": "0",
            "Data_Atualizacao": "2025-03-16 02:52:18.127",
            "Data_Hora_Medicao": "2025-03-16 02:00:00.0",
            "Vazao_Adotada": "4.90",
            "Vazao_Adotada_Status": "0"
        },
        {
            "Chuva_Adotada": "0.00",
            "Chuva_Adotada_Status": "0",
            "Cota_Adotada": "67.00",
            "Cota_Adotada_Status": "0",
            "Data_Atualizacao": "2025-03-16 04:16:47.16",
            "Data_Hora_Medicao": "2025-03-16 03:00:00.0",
            "Vazao_Adotada": "4.90",
            "Vazao_Adotada_Status": "0"
        },
        {
            "Chuva_Adotada": "0.00",
            "Chuva_Adotada_Status": "0",
            "Cota_Adotada": "67.00",
            "Cota_Adotada_Status": "0",
            "Data_Atualizacao": "2025-03-16 04:16:47.16",
            "Data_Hora_Medicao": "2025-03-16 04:00:00.0",
            "Vazao_Adotada": "4.90",
            "Vazao_Adotada_Status": "0"
        },
        {
            "Chuva_Adotada": "0.00",
            "Chuva_Adotada_Status": "0",
            "Cota_Adotada": "67.00",
            "Cota_Adotada_Status": "0",
            "Data_Atualizacao": "2025-03-16 05:24:10.977",
            "Data_Hora_Medicao": "2025-03-16 05:00:00.0",
            "Vazao_Adotada": "4.90",
            "Vazao_Adotada_Status": "0"
        },
        {
            "Chuva_Adotada": "0.00",
            "Chuva_Adotada_Status": "0",
            "Cota_Adotada": "67.00",
            "Cota_Adotada_Status": "0",
            "Data_Atualizacao": "2025-03-16 06:31:44.057",
            "Data_Hora_Medicao": "2025-03-16 06:00:00.0",
            "Vazao_Adotada": "4.90",
            "Vazao_Adotada_Status": "0"
        },
        {
            "Chuva_Adotada": "0.00",
            "Chuva_Adotada_Status": "0",
            "Cota_Adotada": "67.00",
            "Cota_Adotada_Status": "0",
            "Data_Atualizacao": "2025-03-16 07:39:12.763",
            "Data_Hora_Medicao": "2025-03-16 07:00:00.0",
            "Vazao_Adotada": "4.90",
            "Vazao_Adotada_Status": "0"
        },
        {
            "Chuva_Adotada": "0.00",
            "Chuva_Adotada_Status": "0",
            "Cota_Adotada": "68.00",
            "Cota_Adotada_Status": "0",
            "Data_Atualizacao": "2025-03-16 11:35:36.46",
            "Data_Hora_Medicao": "2025-03-16 08:00:00.0",
            "Vazao_Adotada": "5.10",
            "Vazao_Adotada_Status": "0"
        },
        {
            "Chuva_Adotada": "0.00",
            "Chuva_Adotada_Status": "0",
            "Cota_Adotada": "67.00",
            "Cota_Adotada_Status": "0",
            "Data_Atualizacao": "2025-03-16 11:52:47.643",
            "Data_Hora_Medicao": "2025-03-16 09:00:00.0",
            "Vazao_Adotada": "4.90",
            "Vazao_Adotada_Status": "0"
        },
        {
            "Chuva_Adotada": "0.00",
            "Chuva_Adotada_Status": "0",
            "Cota_Adotada": "67.00",
            "Cota_Adotada_Status": "0",
            "Data_Atualizacao": "2025-03-16 12:59:58.167",
            "Data_Hora_Medicao": "2025-03-16 10:00:00.0",
            "Vazao_Adotada": "4.90",
            "Vazao_Adotada_Status": "0"
        },
        {
            "Chuva_Adotada": "0.00",
            "Chuva_Adotada_Status": "0",
            "Cota_Adotada": "67.00",
            "Cota_Adotada_Status": "0",
            "Data_Atualizacao": "2025-03-16 12:59:58.17",
            "Data_Hora_Medicao": "2025-03-16 11:00:00.0",
            "Vazao_Adotada": "4.90",
            "Vazao_Adotada_Status": "0"
        },
        {
            "Chuva_Adotada": "0.00",
            "Chuva_Adotada_Status": "0",
            "Cota_Adotada": "68.00",
            "Cota_Adotada_Status": "0",
            "Data_Atualizacao": "2025-03-16 12:59:58.167",
            "Data_Hora_Medicao": "2025-03-16 12:00:00.0",
            "Vazao_Adotada": "5.10",
            "Vazao_Adotada_Status": "0"
        },
        {
            "Chuva_Adotada": "0.00",
            "Chuva_Adotada_Status": "0",
            "Cota_Adotada": "67.00",
            "Cota_Adotada_Status": "0",
            "Data_Atualizacao": "2025-03-16 14:58:19.297",
            "Data_Hora_Medicao": "2025-03-16 14:00:00.0",
            "Vazao_Adotada": "4.90",
            "Vazao_Adotada_Status": "0"
        },
        {
            "Chuva_Adotada": "0.00",
            "Chuva_Adotada_Status": "0",
            "Cota_Adotada": "67.00",
            "Cota_Adotada_Status": "0",
            "Data_Atualizacao": "2025-03-16 15:48:50.417",
            "Data_Hora_Medicao": "2025-03-16 15:00:00.0",
            "Vazao_Adotada": "4.90",
            "Vazao_Adotada_Status": "0"
        },
        {
            "Chuva_Adotada": "0.00",
            "Chuva_Adotada_Status": "0",
            "Cota_Adotada": "67.00",
            "Cota_Adotada_Status": "0",
            "Data_Atualizacao": "2025-03-16 16:39:28.317",
            "Data_Hora_Medicao": "2025-03-16 16:00:00.0",
            "Vazao_Adotada": "4.90",
            "Vazao_Adotada_Status": "0"
        },
        {
            "Chuva_Adotada": "0.80",
            "Chuva_Adotada_Status": "0",
            "Cota_Adotada": "67.00",
            "Cota_Adotada_Status": "0",
            "Data_Atualizacao": "2025-03-16 19:45:13.567",
            "Data_Hora_Medicao": "2025-03-16 17:00:00.0",
            "Vazao_Adotada": "4.90",
            "Vazao_Adotada_Status": "0"
        },
        {
            "Chuva_Adotada": "0.00",
            "Chuva_Adotada_Status": "0",
            "Cota_Adotada": "66.00",
            "Cota_Adotada_Status": "0",
            "Data_Atualizacao": "2025-03-16 19:45:13.627",
            "Data_Hora_Medicao": "2025-03-16 18:00:00.0",
            "Vazao_Adotada": "4.71",
            "Vazao_Adotada_Status": "0"
        },
        {
            "Chuva_Adotada": "0.00",
            "Chuva_Adotada_Status": "0",
            "Cota_Adotada": "67.00",
            "Cota_Adotada_Status": "0",
            "Data_Atualizacao": "2025-03-16 20:35:50.847",
            "Data_Hora_Medicao": "2025-03-16 20:00:00.0",
            "Vazao_Adotada": "4.90",
            "Vazao_Adotada_Status": "0"
        },
        {
            "Chuva_Adotada": "0.00",
            "Chuva_Adotada_Status": "0",
            "Cota_Adotada": "66.00",
            "Cota_Adotada_Status": "0",
            "Data_Atualizacao": "2025-03-16 21:26:29.43",
            "Data_Hora_Medicao": "2025-03-16 21:00:00.0",
            "Vazao_Adotada": "4.71",
            "Vazao_Adotada_Status": "0"
        },
        {
            "Chuva_Adotada": "0.00",
            "Chuva_Adotada_Status": "0",
            "Cota_Adotada": "66.00",
            "Cota_Adotada_Status": "0",
            "Data_Atualizacao": "2025-03-16 22:51:09.58",
            "Data_Hora_Medicao": "2025-03-16 22:00:00.0",
            "Vazao_Adotada": "4.71",
            "Vazao_Adotada_Status": "0"
        },
        {
            "Chuva_Adotada": "0.00",
            "Chuva_Adotada_Status": "0",
            "Cota_Adotada": "67.00",
            "Cota_Adotada_Status": "0",
            "Data_Atualizacao": "2025-03-16 23:42:12.787",
            "Data_Hora_Medicao": "2025-03-16 23:00:00.0",
            "Vazao_Adotada": "4.90",
            "Vazao_Adotada_Status": "0"
        }
    ]
}