{
    "codigoestacao": "17385000",
    "data": "2025-01-29",
    "dados": [
        {
            "Chuva_Adotada": "0.00",
            "Chuva_Adotada_Status": "0",
            "Cota_Adotada": "412.00",
            "Cota_Adotada_Status": "0",
            "Data_Atualizacao": "2025-01-29 01:34:53.887",
            "Data_Hora_Medicao": "2025-01-29 01:00:00.0",
            "Vazao_Adotada": "21.58",
            "Vazao_Adotada_Status": "0"
        },
        {
            "Chuva_Adotada": "0.00",
            "Chuva_Adotada_Status": "0",
            "Cota_Adotada": "414.00",
            "Cota_Adotada_Status": "0",
            "Data_Atualizacao": "2025-01-29 01:34:53.897",
            "Data_Hora_Medicao": "2025-01-29 00:00:00.0",
            "Vazao_Adotada": "21.76",
            "Vazao_Adotada_Status": "0"
        },
        {
            "Chuva_Adotada": "0.00",
            "Chuva_Adotada_Status": "0",
            "Cota_Adotada": "411.00",
            "Cota_Adotada_Status": "0",
            "Data_Atualizacao": "2025-01-29 02:08:26.133",
            "Data_Hora_Medicao": "2025-01-29 02:00:00.0",
            "Vazao_Adotada": "21.49",
            "Vazao_Adotada_Status": "0"
        },
        {
            "Chuva_Adotada": "0.00",
            "Chuva_Adotada_Status": "0",
            "Cota_Adotada": "410.00",
            "Cota_Adotada_Status": "0",
            "Data_Atualizacao": "2025-01-29 03:16:23.97",
            "Data_Hora_Medicao": "2025-01-29 03:00:00.0",
            "Vazao_Adotada": "21.40",
            "Vazao_Adotada_Status": "0"
        },
        {
            "Chuva_Adotada": "0.00",
            "Chuva_Adotada_Status": "0",
            "Cota_Adotada": "408.00",
            "Cota_Adotada_Status": "0",
            "Data_Atualizacao": "2025-01-29 04:06:41.83",
            "Data_Hora_Medicao": "2025-01-29 04:00:00.0",
            "Vazao_Adotada": "21.21",
            "Vazao_Adotada_Status": "0"
        },
        {
            "Chuva_Adotada": "0.00",
            "Chuva_Adotada_Status": "0",
            "Cota_Adotada": "406.00",
            "Cota_Adotada_Status": "0",
            "Data_Atualizacao": "2025-01-29 05:14:43.48",
            "Data_Hora_Medicao": "2025-01-29 05:00:00.0",
            "Vazao_Adotada": "21.03",
            "Vazao_Adotada_Status": "0"
        },
        {
            "Chuva_Adotada": "0.00",
            "Chuva_Adotada_Status": "0",
            "Cota_Adotada": "405.00",
            "Cota_Adotada_Status": "0",
            "Data_Atualizacao": "2025-01-29 06:04:45.8",
            "Data_Hora_Medicao": "2025-01-29 06:00:00.0",
            "Vazao_Adotada": "20.94",
            "Vazao_Adotada_Status": "0"
        },
        {
            "Chuva_Adotada": "0.00",
            "Chuva_Adotada_Status": "0",
            "Cota_Adotada": "403.00",
            "Cota_Adotada_Status": "0",
            "Data_Atualizacao": "2025-01-29 07:12:29.917",
            "Data_Hora_Medicao": "2025-01-29 07:00:00.0",
            "Vazao_Adotada": "20.77",
            "Vazao_Adotada_Status": "0"
        },
        {
            "Chuva_Adotada": "0.00",
            "Chuva_Adotada_Status": "0",
            "Cota_Adotada": "401.00",
            "Cota_Adotada_Status": "0",
            "Data_Atualizacao": "2025-01-29 08:20:00.927",
            "Data_Hora_Medicao": "2025-01-29 08:00:00.0",
            "Vazao_Adotada": "20.59",
            "Vazao_Adotada_Status": "0"
        },
        {
            "Chuva_Adotada": "0.00",
            "Chuva_Adotada_Status": "0",
            "Cota_Adotada": "400.00",
            "Cota_Adotada_Status": "0",
            "Data_Atualizacao": "2025-01-29 09:10:41.15",
            "Data_Hora_Medicao": "2025-01-29 09:00:00.0",
            "Vazao_Adotada": "20.50",
            "Vazao_Adotada_Status": "0"
        },
        {
            "Chuva_Adotada": "0.00",
            "Chuva_Adotada_Status": "0",
            "Cota_Adotada": "398.00",
            "Cota_Adotada_Status": "0",
            "Data_Atualizacao": "2025-01-29 10:18:14.377",
            "Data_Hora_Medicao": "2025-01-29 10:00:00.0",
            "Vazao_Adotada": "20.32",
            "Vazao_Adotada_Status": "0"
        },
        {
            "Chuva_Adotada": "0.00",
            "Chuva_Adotada_Status": "0",
            "Cota_Adotada": "397.00",
            "Cota_Adotada_Status": "0",
            "Data_Atualizacao": "2025-01-29 11:08:48.22",
            "Data_Hora_Medicao": "2025-01-29 11:00:00.0",
            "Vazao_Adotada": "20.23",
            "Vazao_Adotada_Status": "0"
        },
        {
            "Chuva_Adotada": "0.00",
            "Chuva_Adotada_Status": "0",
            "Cota_Adotada": "397.00",
            "Cota_Adotada_Status": "0",
            "Data_Atualizacao": "2025-01-29 12:16:53.193",
            "Data_Hora_Medicao": "2025-01-29 12:00:00.0",
            "Vazao_Adotada": "20.23",
            "Vazao_Adotada_Status": "0"
        },
        {
            "Chuva_Adotada": "0.20",
            "Chuva_Adotada_Status": "0",
            "Cota_Adotada": "394.00",
            "Cota_Adotada_Status": "0",
            "Data_Atualizacao": "2025-01-29 13:06:58.313",
            "Data_Hora_Medicao": "2025-01-29 13:00:00.0",
            "Vazao_Adotada": "19.96",
            "Vazao_Adotada_Status": "0"
        },
        {
            "Chuva_Adotada": "0.00",
            "Chuva_Adotada_Status": "0",
            "Cota_Adotada": "392.00",
            "Cota_Adotada_Status": "0",
            "Data_Atualizacao": "2025-01-29 14:14:49.803",
            "Data_Hora_Medicao": "2025-01-29 14:00:00.0",
            "Vazao_Adotada": "19.79",
            "Vazao_Adotada_Status": "0"
        },
        {
            "Chuva_Adotada": "0.00",
            "Chuva_Adotada_Status": "0",
            "Cota_Adotada": "392.00",
            "Cota_Adotada_Status": "0",
            "Data_Atualizacao": "2025-01-29 15:05:06.873",
            "Data_Hora_Medicao": "2025-01-29 15:00:00.0",
            "Vazao_Adotada": "19.79",
            "Vazao_Adotada_Status": "0"
        },
        {
            "Chuva_Adotada": "0.00",
            "Chuva_Adotada_Status": "0",
            "Cota_Adotada": "390.00",
            "Cota_Adotada_Status": "0",
            "Data_Atualizacao": "2025-01-29 16:30:33.11",
            "Data_Hora_Medicao": "2025-01-29 16:00:00.0",
            "Vazao_Adotada": "19.61",
            "Vazao_Adotada_Status": "0"
        },
        {
            "Chuva_Adotada": "0.40",
            "Chuva_Adotada_Status": "0",
            "Cota_Adotada": "389.00",
            "Cota_Adotada_Status": "0",
            "Data_Atualizacao": "2025-01-29 17:21:38.817",
            "Data_Hora_Medicao": "2025-01-29 17:00:00.0",
            "Vazao_Adotada": "19.52",
            "Vazao_Adotada_Status": "0"
        },
        {
            "Chuva_Adotada": "1.20",
            "Chuva_Adotada_Status": "0",
            "Cota_Adotada": "388.00",
            "Cota_Adotada_Status": "0",
            "Data_Atualizacao": "2025-01-29 18:11:07.383",
            "Data_Hora_Medicao": "2025-01-29 18:00:00.0",
            "Vazao_Adotada": "19.43",
            "Vazao_Adotada_Status": "0"
        },
        {
            "Chuva_Adotada": "0.40",
            "Chuva_Adotada_Status": "0",
            "Cota_Adotada": "387.00",
            "Cota_Adotada_Status": "0",
            "Data_Atualizacao": "2025-01-29 19:19:15.647",
            "Data_Hora_Medicao": "2025-01-29 19:00:00.0",
            "Vazao_Adotada": "19.35",
            "Vazao_Adotada_Status": "0"
        },
        {
            "Chuva_Adotada": "1.00",
            "Chuva_Adotada_Status": "0",
            "Cota_Adotada": "386.00",
            "Cota_Adotada_Status": "0",
            "Data_Atualizacao": "2025-01-29 20:09:01.577",
            "Data_Hora_Medicao": "2025-01-29 20:00:00.0",
            "Vazao_Adotada": "19.26",
            "Vazao_Adotada_Status": "0"
        },
        {
            "Chuva_Adotada": "0.00",
            "Chuva_Adotada_Status": "0",
            "Cota_Adotada": "384.00",
            "Cota_Adotada_Status": "0",
            "Data_Atualizacao": "2025-01-29 21:16:46.733",
            "Data_Hora_Medicao": "2025-01-29 21:00:00.0",
            "Vazao_Adotada": "19.08",
            "Vazao_Adotada_Status": "0"
        },
        {
            "Chuva_Adotada": "0.00",
            "Chuva_Adotada_Status": "0",
            "Cota_Adotada": "384.00",
            "Cota_Adotada_Status": "0",
            "Data_Atualizacao": "2025-01-29 22:07:12.25",
            "Data_Hora_Medicao": "2025-01-29 22:00:00.0",
            "Vazao_Adotada": "19.08",
            "Vazao_Adotada_Status": "0"
        },
        {
            "Chuva_Adotada": "0.00",
            "Chuva_Adotada_Status": "0",
            "Cota_Adotada": "383.00",
            "Cota_Adotada_Status": "0",
            "Data_Atualizacao": "2025-01-29 23:49:10.197",
            "Data_Hora_Medicao": "2025-01-29 23:00:00.0",
            "Vazao_Adotada": "18.99",
            "Vazao_Adotada_Status": "0"
        }
    ]
}